datamechanics_airflow_plugin/__init__.py
datamechanics_airflow_plugin/application_state.py
datamechanics_airflow_plugin/hook.py
datamechanics_airflow_plugin/operator.py
datamechanics_airflow_plugin/plugin.py
datamechanics_airflow_plugin-1.1.1.dist-info/LICENSE
datamechanics_airflow_plugin-1.1.1.dist-info/METADATA
datamechanics_airflow_plugin-1.1.1.dist-info/WHEEL
datamechanics_airflow_plugin-1.1.1.dist-info/entry_points.txt
datamechanics_airflow_plugin-1.1.1.dist-info/top_level.txt
datamechanics_airflow_plugin-1.1.1.dist-info/RECORD
