Metadata-Version: 2.1
Name: datamechanics-airflow-plugin
Version: 1.1.1
Summary: An Airflow plugin to launch and monitor Spark applications on the Data Mechanics platform
Home-page: https://github.com/datamechanics/datamechanics_airflow_plugin
Author: Data Mechanics Engineering Team
Author-email: engineering@datamechanics.co
License: Apache Software License 2.0
Keywords: datamechanics_airflow_plugin
Platform: UNKNOWN
Classifier: Development Status :: 4 - Beta
Classifier: Intended Audience :: Developers
Classifier: License :: OSI Approved :: Apache Software License
Classifier: Natural Language :: English
Classifier: Programming Language :: Python :: 3
Classifier: Programming Language :: Python :: 3.5
Classifier: Programming Language :: Python :: 3.6
Classifier: Programming Language :: Python :: 3.7
Classifier: Programming Language :: Python :: 3.8
Requires-Python: >=3.5
Requires-Dist: requests
Requires-Dist: apache-airflow (>=1.10.0)
